AUTHORS.rst
CHANGELOG.rst
LICENSE.txt
README.rst
ledfx-2.1.2.dist-info/METADATA
ledfx-2.1.2.dist-info/WHEEL
ledfx-2.1.2.dist-info/entry_points.txt
ledfx-2.1.2.dist-info/licenses/LICENSE.txt
ledfx.env
ledfx/__init__.py
ledfx/__main__.py
ledfx/api/__init__.py
ledfx/api/audio_devices.py
ledfx/api/check_for_updates.py
ledfx/api/clients.py
ledfx/api/colors.py
ledfx/api/com_ports.py
ledfx/api/config.py
ledfx/api/device.py
ledfx/api/devices.py
ledfx/api/effect.py
ledfx/api/effects.py
ledfx/api/find_devices.py
ledfx/api/find_launchpad.py
ledfx/api/find_openrgb.py
ledfx/api/generate_ts_types.py
ledfx/api/get_gif_frames.py
ledfx/api/get_image.py
ledfx/api/get_nanoleaf_token.py
ledfx/api/info.py
ledfx/api/integration_qlc.py
ledfx/api/integration_spotify.py
ledfx/api/integrations.py
ledfx/api/log.py
ledfx/api/notification.py
ledfx/api/ping.py
ledfx/api/playlists.py
ledfx/api/playlists_id.py
ledfx/api/power.py
ledfx/api/presets.py
ledfx/api/scenes.py
ledfx/api/schema.py
ledfx/api/utils.py
ledfx/api/virtual.py
ledfx/api/virtual_effects.py
ledfx/api/virtual_effects_delete.py
ledfx/api/virtual_effects_fallback.py
ledfx/api/virtual_presets.py
ledfx/api/virtual_tools.py
ledfx/api/virtuals.py
ledfx/api/virtuals_tools.py
ledfx/api/websocket.py
ledfx/color.py
ledfx/config.py
ledfx/consts.py
ledfx/core.py
ledfx/dedupequeue.py
ledfx/devices/__init__.py
ledfx/devices/adalight.py
ledfx/devices/artnet.py
ledfx/devices/ddp.py
ledfx/devices/dummy.py
ledfx/devices/e131.py
ledfx/devices/govee.py
ledfx/devices/hue.py
ledfx/devices/launchpad.py
ledfx/devices/launchpad_lib.py
ledfx/devices/lifx.py
ledfx/devices/nanoleaf.py
ledfx/devices/open_pixel_control.py
ledfx/devices/openrgb.py
ledfx/devices/osc.py
ledfx/devices/packets.py
ledfx/devices/rpi_ws281x.py
ledfx/devices/twinkly_squares.py
ledfx/devices/udp.py
ledfx/devices/utils/rgbw_conversion.py
ledfx/devices/utils/socket_singleton.py
ledfx/devices/wled.py
ledfx/devices/zengee.py
ledfx/effects/__init__.py
ledfx/effects/audio.py
ledfx/effects/bands.py
ledfx/effects/bands_matrix.py
ledfx/effects/bar.py
ledfx/effects/blade_power_plus.py
ledfx/effects/bleep.py
ledfx/effects/blender.py
ledfx-2.1.2.dist-info/RECORD
